[
    {
        "id":"H001",
        "title":"尤亚头层牛皮时尚加大沙发组合",
        "time":"[00:30~01:19]",
        "imgurl":"img/hot1.jpg",
        "url":"#",
        "price":5998.00
    },
    {
        "id":"H002",
        "title":"Anci智能RO反渗透净水机",
        "time":"[01:20~02:03]",
        "imgurl":"img/hot2.jpg",
        "url":"#",
        "price":1980.00
    },
    {
        "id":"H003",
        "title":"德国UKS-12L智能恒温热水器",
        "time":"[02:05~02:48]",
        "imgurl":"img/hot3.jpg",
        "url":"#",
        "price":1680.00
    },
    {
        "id":"H004",
        "title":"德国UKS-16L智能恒温热水器",
        "time":"[02:05~02:48]",
        "imgurl":"img/hot5.jpg",
        "url":"#",
        "price":2680.00
    }
]